finder_of_mechalinos/__init__.py
finder_of_mechalinos/main.py
finder_of_mechalinos-1.0.2.dist-info/licenses/LICENSE
finder_of_mechalinos-1.0.2.dist-info/METADATA
finder_of_mechalinos-1.0.2.dist-info/WHEEL
finder_of_mechalinos-1.0.2.dist-info/entry_points.txt
finder_of_mechalinos-1.0.2.dist-info/top_level.txt
finder_of_mechalinos-1.0.2.dist-info/RECORD
