Metadata-Version: 2.4
Name: finder-of-mechalinos
Version: 1.0.2
Summary: Tool to discover Mechalino robots on a local network
Author: Khalil Youssefi
Author-email: Khalil Youssefi <kh4lil@outlook.com>
License: MIT
Project-URL: Homepage, https://github.com/Khalil-Youssefi/finder-of-mechalinos
Requires-Python: >=3.8
License-File: LICENSE
Requires-Dist: scapy>=2.5
Requires-Dist: netifaces>=0.11
Dynamic: author
Dynamic: license-file
